Moore.vhdl
Library IEEE;
use IEEE.std_logic_1164.all;
entity MOORE is -- Moore machine
port (X, CLOCK: in STD_LOGIC;
Z: out STD_LOGIC);
end;
architecture BEHAVIOR of MOORE is
type STATE_TYPE is (S0, S1, S2, S3);
signal CURRENT_STATE, NEXT_STATE: STATE_TYPE;
begin
-- Process to hold combinational logic
COMBIN: process (CURRENT_STATE, X)
begin
case CURRENT_STATE is
when S0 =>
Z <= '0';
if X = '0' then
NEXT_STATE <= S0;
else
NEXT_STATE <= S2;
end if;
when S1 =>
Z <= '1';
if X = '0' then
NEXT_STATE <= S0;
else
NEXT_STATE <= S2;
end if;
when S2 =>
Z <= '1';
if X = '0' then
NEXT_STATE <= S2;
else
NEXT_STATE <= S3;
end if;
when S3 =>
Z <= '0';
if X = '0' then
NEXT_STATE <= S3;
else
NEXT_STATE <= S1;
end if;
end case;
end process;
-- Process to hold synchronous elements (flip-flops)
SYNCH: process
begin
wait until CLOCK'event and CLOCK = '1';
CURRENT_STATE <= NEXT_STATE;
end process;
end BEHAVIOR;

moore_tb.vhdl
Library IEEE;
use IEEE.std_logic_1164.all;
entity TB_MOORE is
end;
architecture TESTBENCH of TB_MOORE is
signal CLK : std_logic;
signal X : std_logic;
signal Z : std_logic;
component MOORE
Port (
X, CLOCK: in STD_LOGIC;
Z: out STD_LOGIC
);
end component;
procedure check(signal Z : in std_logic;
constant Expected : in std_logic;
constant timepoint : in time) is
begin
assert ( Z /= Expected OR timepoint /= now )
report "Value on Z is OK"
severity NOTE;
end;
begin
UUT : MOORE
Port Map (X, CLK, Z);
-- CLOCK STIMULI OF 100 NS TIME PERIOD
CLOCK: process
begin
CLK <= '0', '1' after 50 ns;
wait for 100 ns;
end process;
-- X input STIMULI
X_Stimuli: process
begin
X <= '1', '0' after 1000 ns;
wait for 2000 ns;
end process;
-- Assert Process
check(Z,'1', 50 ns);
check(Z,'0', 150 ns);
check(Z,'1', 250 ns);
check(Z,'0', 450 ns);
end TESTBENCH;
configuration CFG_TB_MOORE of TB_MOORE is
for TESTBENCH
for UUT : MOORE
end for;
end for;
end;

mooretb.vcd
$date
  Sat Feb 12 21:07:56 2022
$end
$version
  GHDL v0
$end
$timescale
  1 fs
$end
$scope module standard $end
$upscope $end
$scope module std_logic_1164 $end
$upscope $end
$scope module tb_moore $end
$var reg 1 ! clk $end
$var reg 1 " x $end
$var reg 1 # z $end
$scope module uut $end
$var reg 1 $ x $end
$var reg 1 % clock $end
$var reg 1 & z $end
$comment current_state is not handled $end
$comment next_state is not handled $end
$upscope $end
$upscope $end
$enddefinitions $end
#0
0!
1"
0#
1$
0%
0&
#50000000
1!
1#
1%
1&
#100000000
0!
0%
#150000000
1!
0#
1%
0&
#200000000
0!
0%
#250000000
1!
1#
1%
1&
#300000000
0!
0%
#350000000
1!
1%
#400000000
0!
0%
#450000000
1!
0#
1%
0&
#500000000
0!
0%
#550000000
1!
1#
1%
1&
#600000000
0!
0%
#650000000
1!
1%
#700000000
0!
0%
#750000000
1!
0#
1%
0&
#800000000
0!
0%
#850000000
1!
1#
1%
1&
#900000000
0!
0%
#950000000
1!
1%
#1000000000
0!
0"
0$
0%
#1050000000
1!
1%
#1100000000
0!
0%
#1150000000
1!
1%
#1200000000
0!
0%
#1250000000
1!
1%
#1300000000
0!
0%
#1350000000
1!
1%
#1400000000
0!
0%
#1450000000
1!
1%
#1500000000
0!
0%
#1550000000
1!
1%
#1600000000
0!
0%
#1650000000
1!
1%
#1700000000
0!
0%
#1750000000
1!
1%
#1800000000
0!
0%
#1850000000
1!
1%
#1900000000
0!
0%
#1950000000
1!
1%
#2000000000
0!
1"
1$
0%
#2050000000
1!
0#
1%
0&
#2100000000
0!
0%
#2150000000
1!
1#
1%
1&
#2200000000
0!
0%
#2250000000
1!
1%
#2300000000
0!
0%
#2350000000
1!
0#
1%
0&
#2400000000
0!
0%
#2450000000
1!
1#
1%
1&
#2500000000
0!
0%
#2550000000
1!
1%
#2600000000
0!
0%
#2650000000
1!
0#
1%
0&
#2700000000
0!
0%
#2750000000
1!
1#
1%
1&
#2800000000
0!
0%
#2850000000
1!
1%
#2900000000
0!
0%
#2950000000
1!
0#
1%
0&
#3000000000
0!
0"
0$
0%
#3050000000
1!
1%
#3100000000
0!
0%
#3150000000
1!
1%
#3200000000
0!
0%
#3250000000
1!
1%
#3300000000
0!
0%
#3350000000
1!
1%
#3400000000
0!
0%
#3450000000
1!
1%
#3500000000
0!
0%
#3550000000
1!
1%
#3600000000
0!
0%
#3650000000
1!
1%
#3700000000
0!
0%
#3750000000
1!
1%
#3800000000
0!
0%
#3850000000
1!
1%
#3900000000
0!
0%
#3950000000
1!
1%
#4000000000
0!
1"
1$
0%
#4050000000
1!
1#
1%
1&
#4100000000
0!
0%
#4150000000
1!
1%
#4200000000
0!
0%
#4250000000
1!
0#
1%
0&
#4300000000
0!
0%
#4350000000
1!
1#
1%
1&
#4400000000
0!
0%
#4450000000
1!
1%
#4500000000
0!
0%
#4550000000
1!
0#
1%
0&
#4600000000
0!
0%
#4650000000
1!
1#
1%
1&
#4700000000
0!
0%
#4750000000
1!
1%
#4800000000
0!
0%
#4850000000
1!
0#
1%
0&
#4900000000
0!
0%
#4950000000
1!
1#
1%
1&
#5000000000
0!
0"
0$
0%
#5050000000
1!
0#
1%
0&
#5100000000
0!
0%
#5150000000
1!
1%
#5200000000
0!
0%
#5250000000
1!
1%
#5300000000
0!
0%
#5350000000
1!
1%
#5400000000
0!
0%
#5450000000
1!
1%
#5500000000
0!
0%
#5550000000
1!
1%
#5600000000
0!
0%
#5650000000
1!
1%
#5700000000
0!
0%
#5750000000
1!
1%
#5800000000
0!
0%
#5850000000
1!
1%
#5900000000
0!
0%
#5950000000
1!
1%
#6000000000
0!
1"
1$
0%
#6050000000
1!
1#
1%
1&
#6100000000
0!
0%
#6150000000
1!
0#
1%
0&
#6200000000
0!
0%
#6250000000
1!
1#
1%
1&
#6300000000
0!
0%
#6350000000
1!
1%
#6400000000
0!
0%
#6450000000
1!
0#
1%
0&
#6500000000
0!
0%
#6550000000
1!
1#
1%
1&
#6600000000
0!
0%
#6650000000
1!
1%
#6700000000
0!
0%
#6750000000
1!
0#
1%
0&
#6800000000
0!
0%
#6850000000
1!
1#
1%
1&
#6900000000
0!
0%
#6950000000
1!
1%
#7000000000
0!
0"
0$
0%
#7050000000
1!
1%
#7100000000
0!
0%
#7150000000
1!
1%
#7200000000
0!
0%
#7250000000
1!
1%
#7300000000
0!
0%
#7350000000
1!
1%
#7400000000
0!
0%
#7450000000
1!
1%
#7500000000
0!
0%
#7550000000
1!
1%
#7600000000
0!
0%
#7650000000
1!
1%
#7700000000
0!
0%
#7750000000
1!
1%
#7800000000
0!
0%
#7850000000
1!
1%
#7900000000
0!
0%
#7950000000
1!
1%
#8000000000
0!
1"
1$
0%
#8050000000
1!
0#
1%
0&
#8100000000
0!
0%
#8150000000
1!
1#
1%
1&
#8200000000
0!
0%
#8250000000
1!
1%
#8300000000
0!
0%
#8350000000
1!
0#
1%
0&
#8400000000
0!
0%
#8450000000
1!
1#
1%
1&
#8500000000
0!
0%
#8550000000
1!
1%
#8600000000
0!
0%
#8650000000
1!
0#
1%
0&
#8700000000
0!
0%
#8750000000
1!
1#
1%
1&
#8800000000
0!
0%
#8850000000
1!
1%
#8900000000
0!
0%
#8950000000
1!
0#
1%
0&
#9000000000
0!
0"
0$
0%
#9050000000
1!
1%
#9100000000
0!
0%
#9150000000
1!
1%
#9200000000
0!
0%
#9250000000
1!
1%
#9300000000
0!
0%
#9350000000
1!
1%
#9400000000
0!
0%
#9450000000
1!
1%
#9500000000
0!
0%
#9550000000
1!
1%
#9600000000
0!
0%
#9650000000
1!
1%
#9700000000
0!
0%
#9750000000
1!
1%
#9800000000
0!
0%
#9850000000
1!
1%
#9900000000
0!
0%
#9950000000
1!
1%
#10000000000
0!
1"
1$
0%
#10050000000
1!
1#
1%
1&
#10100000000
0!
0%
#10150000000
1!
1%
#10200000000
0!
0%
#10250000000
1!
0#
1%
0&
#10300000000
0!
0%
#10350000000
1!
1#
1%
1&
#10400000000
0!
0%
#10450000000
1!
1%
#10500000000
0!
0%
#10550000000
1!
0#
1%
0&
#10600000000
0!
0%
#10650000000
1!
1#
1%
1&
#10700000000
0!
0%
#10750000000
1!
1%
#10800000000
0!
0%
#10850000000
1!
0#
1%
0&
#10900000000
0!
0%
#10950000000
1!
1#
1%
1&
#11000000000
0!
0"
0$
0%
#11050000000
1!
0#
1%
0&
#11100000000
0!
0%
#11150000000
1!
1%
#11200000000
0!
0%
#11250000000
1!
1%
#11300000000
0!
0%
#11350000000
1!
1%
#11400000000
0!
0%
#11450000000
1!
1%
#11500000000
0!
0%
#11550000000
1!
1%
#11600000000
0!
0%
#11650000000
1!
1%
#11700000000
0!
0%
#11750000000
1!
1%
#11800000000
0!
0%
#11850000000
1!
1%
#11900000000
0!
0%
#11950000000
1!
1%
#12000000000
0!
1"
1$
0%
#12050000000
1!
1#
1%
1&
#12100000000
0!
0%
#12150000000
1!
0#
1%
0&
#12200000000
0!
0%
#12250000000
1!
1#
1%
1&
#12300000000
0!
0%
#12350000000
1!
1%
#12400000000
0!
0%
#12450000000
1!
0#
1%
0&
#12500000000
0!
0%
#12550000000
1!
1#
1%
1&
#12600000000
0!
0%
#12650000000
1!
1%
#12700000000
0!
0%
#12750000000
1!
0#
1%
0&
#12800000000
0!
0%
#12850000000
1!
1#
1%
1&
#12900000000
0!
0%
#12950000000
1!
1%
#13000000000
0!
0"
0$
0%
#13050000000
1!
1%
#13100000000
0!
0%
#13150000000
1!
1%
#13200000000
0!
0%
#13250000000
1!
1%
#13300000000
0!
0%
#13350000000
1!
1%
#13400000000
0!
0%
#13450000000
1!
1%
#13500000000
0!
0%
#13550000000
1!
1%
#13600000000
0!
0%
#13650000000
1!
1%
#13700000000
0!
0%
#13750000000
1!
1%
#13800000000
0!
0%
#13850000000
1!
1%
#13900000000
0!
0%
#13950000000
1!
1%
#14000000000
0!
1"
1$
0%
#14050000000
1!
0#
1%
0&
#14100000000
0!
0%
#14150000000
1!
1#
1%
1&
#14200000000
0!
0%
#14250000000
1!
1%
#14300000000
0!
0%
#14350000000
1!
0#
1%
0&
#14400000000
0!
0%
#14450000000
1!
1#
1%
1&
#14500000000
0!
0%
#14550000000
1!
1%
#14600000000
0!
0%
#14650000000
1!
0#
1%
0&
#14700000000
0!
0%
#14750000000
1!
1#
1%
1&
#14800000000
0!
0%
#14850000000
1!
1%
#14900000000
0!
0%
#14950000000
1!
0#
1%
0&
#15000000000
0!
0"
0$
0%
#15050000000
1!
1%
#15100000000
0!
0%
#15150000000
1!
1%
#15200000000
0!
0%
#15250000000
1!
1%
#15300000000
0!
0%
#15350000000
1!
1%
#15400000000
0!
0%
#15450000000
1!
1%
#15500000000
0!
0%
#15550000000
1!
1%
#15600000000
0!
0%
#15650000000
1!
1%
#15700000000
0!
0%
#15750000000
1!
1%
#15800000000
0!
0%
#15850000000
1!
1%
#15900000000
0!
0%
#15950000000
1!
1%
#16000000000
0!
1"
1$
0%
#16050000000
1!
1#
1%
1&
#16100000000
0!
0%
#16150000000
1!
1%
#16200000000
0!
0%
#16250000000
1!
0#
1%
0&
#16300000000
0!
0%
#16350000000
1!
1#
1%
1&
#16400000000
0!
0%
#16450000000
1!
1%
#16500000000
0!
0%
#16550000000
1!
0#
1%
0&
#16600000000
0!
0%
#16650000000
1!
1#
1%
1&
#16700000000
0!
0%
#16750000000
1!
1%
#16800000000
0!
0%
#16850000000
1!
0#
1%
0&
#16900000000
0!
0%
#16950000000
1!
1#
1%
1&
#17000000000
0!
0"
0$
0%
#17050000000
1!
0#
1%
0&
#17100000000
0!
0%
#17150000000
1!
1%
#17200000000
0!
0%
#17250000000
1!
1%
#17300000000
0!
0%
#17350000000
1!
1%
#17400000000
0!
0%
#17450000000
1!
1%
#17500000000
0!
0%
#17550000000
1!
1%
#17600000000
0!
0%
#17650000000
1!
1%
#17700000000
0!
0%
#17750000000
1!
1%
#17800000000
0!
0%
#17850000000
1!
1%
#17900000000
0!
0%
#17950000000
1!
1%
#18000000000
0!
1"
1$
0%
#18050000000
1!
1#
1%
1&
#18100000000
0!
0%
#18150000000
1!
0#
1%
0&
#18200000000
0!
0%
#18250000000
1!
1#
1%
1&
#18300000000
0!
0%
#18350000000
1!
1%
#18400000000
0!
0%
#18450000000
1!
0#
1%
0&
#18500000000
0!
0%
#18550000000
1!
1#
1%
1&
#18600000000
0!
0%
#18650000000
1!
1%
#18700000000
0!
0%
#18750000000
1!
0#
1%
0&
#18800000000
0!
0%
#18850000000
1!
1#
1%
1&
#18900000000
0!
0%
#18950000000
1!
1%
#19000000000
0!
0"
0$
0%
#19050000000
1!
1%
#19100000000
0!
0%
#19150000000
1!
1%
#19200000000
0!
0%
#19250000000
1!
1%
#19300000000
0!
0%
#19350000000
1!
1%
#19400000000
0!
0%
#19450000000
1!
1%
#19500000000
0!
0%
#19550000000
1!
1%
#19600000000
0!
0%
#19650000000
1!
1%
#19700000000
0!
0%
#19750000000
1!
1%
#19800000000
0!
0%
#19850000000
1!
1%
#19900000000
0!
0%
#19950000000
1!
1%
#20000000000
0!
1"
1$
0%
#20050000000
1!
0#
1%
0&
#20100000000
0!
0%
#20150000000
1!
1#
1%
1&
#20200000000
0!
0%
#20250000000
1!
1%
#20300000000
0!
0%
#20350000000
1!
0#
1%
0&
#20400000000
0!
0%
#20450000000
1!
1#
1%
1&
#20500000000
0!
0%
#20550000000
1!
1%
#20600000000
0!
0%
#20650000000
1!
0#
1%
0&
#20700000000
0!
0%
#20750000000
1!
1#
1%
1&
#20800000000
0!
0%
#20850000000
1!
1%
#20900000000
0!
0%
#20950000000
1!
0#
1%
0&
#21000000000
0!
0"
0$
0%
#21050000000
1!
1%
#21100000000
0!
0%
#21150000000
1!
1%
#21200000000
0!
0%
#21250000000
1!
1%
#21300000000
0!
0%
#21350000000
1!
1%
#21400000000
0!
0%
#21450000000
1!
1%
#21500000000
0!
0%
#21550000000
1!
1%
#21600000000
0!
0%
#21650000000
1!
1%
#21700000000
0!
0%
#21750000000
1!
1%
#21800000000
0!
0%
#21850000000
1!
1%
#21900000000
0!
0%
#21950000000
1!
1%
#22000000000
0!
1"
1$
0%
#22050000000
1!
1#
1%
1&
#22100000000
0!
0%
#22150000000
1!
1%
#22200000000
0!
0%
#22250000000
1!
0#
1%
0&
#22300000000
0!
0%
#22350000000
1!
1#
1%
1&
#22400000000
0!
0%
#22450000000
1!
1%
#22500000000
0!
0%
#22550000000
1!
0#
1%
0&
#22600000000
0!
0%
#22650000000
1!
1#
1%
1&
#22700000000
0!
0%
#22750000000
1!
1%
#22800000000
0!
0%
#22850000000
1!
0#
1%
0&
#22900000000
0!
0%
#22950000000
1!
1#
1%
1&
#23000000000
0!
0"
0$
0%
#23050000000
1!
0#
1%
0&
#23100000000
0!
0%
#23150000000
1!
1%
#23200000000
0!
0%
#23250000000
1!
1%
#23300000000
0!
0%
#23350000000
1!
1%
#23400000000
0!
0%
#23450000000
1!
1%
#23500000000
0!
0%
#23550000000
1!
1%
#23600000000
0!
0%
#23650000000
1!
1%
#23700000000
0!
0%
#23750000000
1!
1%
#23800000000
0!
0%
#23850000000
1!
1%
#23900000000
0!
0%
#23950000000
1!
1%
#24000000000
0!
1"
1$
0%
#24050000000
1!
1#
1%
1&
#24100000000
0!
0%
#24150000000
1!
0#
1%
0&
#24200000000
0!
0%
#24250000000
1!
1#
1%
1&
#24300000000
0!
0%
#24350000000
1!
1%
#24400000000
0!
0%
#24450000000
1!
0#
1%
0&
#24500000000
0!
0%
#24550000000
1!
1#
1%
1&
#24600000000
0!
0%
#24650000000
1!
1%
#24700000000
0!
0%
#24750000000
1!
0#
1%
0&
#24800000000
0!
0%
#24850000000
1!
1#
1%
1&
#24900000000
0!
0%
#24950000000
1!
1%
#25000000000
0!
0"
0$
0%
#25050000000
1!
1%
#25100000000
0!
0%
#25150000000
1!
1%
#25200000000
0!
0%
#25250000000
1!
1%
#25300000000
0!
0%
#25350000000
1!
1%
#25400000000
0!
0%
#25450000000
1!
1%
#25500000000
0!
0%
#25550000000
1!
1%
#25600000000
0!
0%
#25650000000
1!
1%
#25700000000
0!
0%
#25750000000
1!
1%
#25800000000
0!
0%
#25850000000
1!
1%
#25900000000
0!
0%
#25950000000
1!
1%
#26000000000
0!
1"
1$
0%
#26050000000
1!
0#
1%
0&
#26100000000
0!
0%
#26150000000
1!
1#
1%
1&
#26200000000
0!
0%
#26250000000
1!
1%
#26300000000
0!
0%
#26350000000
1!
0#
1%
0&
#26400000000
0!
0%
#26450000000
1!
1#
1%
1&
#26500000000
0!
0%
#26550000000
1!
1%
#26600000000
0!
0%
#26650000000
1!
0#
1%
0&
#26700000000
0!
0%
#26750000000
1!
1#
1%
1&
#26800000000
0!
0%
#26850000000
1!
1%
#26900000000
0!
0%
#26950000000
1!
0#
1%
0&
#27000000000
0!
0"
0$
0%
#27050000000
1!
1%
#27100000000
0!
0%
#27150000000
1!
1%
#27200000000
0!
0%
#27250000000
1!
1%
#27300000000
0!
0%
#27350000000
1!
1%
#27400000000
0!
0%
#27450000000
1!
1%
#27500000000
0!
0%
#27550000000
1!
1%
#27600000000
0!
0%
#27650000000
1!
1%
#27700000000
0!
0%
#27750000000
1!
1%
#27800000000
0!
0%
#27850000000
1!
1%
#27900000000
0!
0%
#27950000000
1!
1%
#28000000000
0!
1"
1$
0%
#28050000000
1!
1#
1%
1&
#28100000000
0!
0%
#28150000000
1!
1%
#28200000000
0!
0%
#28250000000
1!
0#
1%
0&
#28300000000
0!
0%
#28350000000
1!
1#
1%
1&
#28400000000
0!
0%
#28450000000
1!
1%
#28500000000
0!
0%
#28550000000
1!
0#
1%
0&
#28600000000
0!
0%
#28650000000
1!
1#
1%
1&
#28700000000
0!
0%
#28750000000
1!
1%
#28800000000
0!
0%
#28850000000
1!
0#
1%
0&
#28900000000
0!
0%
#28950000000
1!
1#
1%
1&
#29000000000
0!
0"
0$
0%
#29050000000
1!
0#
1%
0&
#29100000000
0!
0%
#29150000000
1!
1%
#29200000000
0!
0%
#29250000000
1!
1%
#29300000000
0!
0%
#29350000000
1!
1%
#29400000000
0!
0%
#29450000000
1!
1%
#29500000000
0!
0%
#29550000000
1!
1%
#29600000000
0!
0%
#29650000000
1!
1%
#29700000000
0!
0%
#29750000000
1!
1%
#29800000000
0!
0%
#29850000000
1!
1%
#29900000000
0!
0%
#29950000000
1!
1%
#30000000000
0!
1"
1$
0%
#30050000000
1!
1#
1%
1&
#30100000000
0!
0%
#30150000000
1!
0#
1%
0&
#30200000000
0!
0%
#30250000000
1!
1#
1%
1&
#30300000000
0!
0%
#30350000000
1!
1%
#30400000000
0!
0%
#30450000000
1!
0#
1%
0&
#30500000000
0!
0%
#30550000000
1!
1#
1%
1&
#30600000000
0!
0%
#30650000000
1!
1%
#30700000000
0!
0%
#30750000000
1!
0#
1%
0&
#30800000000
0!
0%
#30850000000
1!
1#
1%
1&
#30900000000
0!
0%
#30950000000
1!
1%
#31000000000
0!
0"
0$
0%
#31050000000
1!
1%
#31100000000
0!
0%
#31150000000
1!
1%
#31200000000
0!
0%
#31250000000
1!
1%
#31300000000
0!
0%
#31350000000
1!
1%
#31400000000
0!
0%
#31450000000
1!
1%
#31500000000
0!
0%
#31550000000
1!
1%
#31600000000
0!
0%
#31650000000
1!
1%
#31700000000
0!
0%
#31750000000
1!
1%
#31800000000
0!
0%
#31850000000
1!
1%
#31900000000
0!
0%
#31950000000
1!
1%
#32000000000
0!
1"
1$
0%
#32050000000
1!
0#
1%
0&
#32100000000
0!
0%
#32150000000
1!
1#
1%
1&
#32200000000
0!
0%
#32250000000
1!
1%
#32300000000
0!
0%
#32350000000
1!
0#
1%
0&
#32400000000
0!
0%
#32450000000
1!
1#
1%
1&
#32500000000
0!
0%
#32550000000
1!
1%
#32600000000
0!
0%
#32650000000
1!
0#
1%
0&
#32700000000
0!
0%
#32750000000
1!
1#
1%
1&
#32800000000
0!
0%
#32850000000
1!
1%
#32900000000
0!
0%
#32950000000
1!
0#
1%
0&
#33000000000
0!
0"
0$
0%
#33050000000
1!
1%
#33100000000
0!
0%
#33150000000
1!
1%
#33200000000
0!
0%
#33250000000
1!
1%
#33300000000
0!
0%
#33350000000
1!
1%
#33400000000
0!
0%
#33450000000
1!
1%
#33500000000
0!
0%
#33550000000
1!
1%
#33600000000
0!
0%
#33650000000
1!
1%
#33700000000
0!
0%
#33750000000
1!
1%
#33800000000
0!
0%
#33850000000
1!
1%
#33900000000
0!
0%
#33950000000
1!
1%
#34000000000
0!
1"
1$
0%
#34050000000
1!
1#
1%
1&
#34100000000
0!
0%
#34150000000
1!
1%
#34200000000
0!
0%
#34250000000
1!
0#
1%
0&
#34300000000
0!
0%
#34350000000
1!
1#
1%
1&
#34400000000
0!
0%
#34450000000
1!
1%
#34500000000
0!
0%
#34550000000
1!
0#
1%
0&
#34600000000
0!
0%
#34650000000
1!
1#
1%
1&
#34700000000
0!
0%
#34750000000
1!
1%
#34800000000
0!
0%
#34850000000
1!
0#
1%
0&
#34900000000
0!
0%
#34950000000
1!
1#
1%
1&
#35000000000
0!
0"
0$
0%
#35050000000
1!
0#
1%
0&
#35100000000
0!
0%
#35150000000
1!
1%
#35200000000
0!
0%
#35250000000
1!
1%
#35300000000
0!
0%
#35350000000
1!
1%
#35400000000
0!
0%
#35450000000
1!
1%
#35500000000
0!
0%
#35550000000
1!
1%
#35600000000
0!
0%
#35650000000
1!
1%
#35700000000
0!
0%
#35750000000
1!
1%
#35800000000
0!
0%
#35850000000
1!
1%
#35900000000
0!
0%
#35950000000
1!
1%
#36000000000
0!
1"
1$
0%
#36050000000
1!
1#
1%
1&
#36100000000
0!
0%
#36150000000
1!
0#
1%
0&
#36200000000
0!
0%
#36250000000
1!
1#
1%
1&
#36300000000
0!
0%
#36350000000
1!
1%
#36400000000
0!
0%
#36450000000
1!
0#
1%
0&
#36500000000
0!
0%
#36550000000
1!
1#
1%
1&
#36600000000
0!
0%
#36650000000
1!
1%
#36700000000
0!
0%
#36750000000
1!
0#
1%
0&
#36800000000
0!
0%
#36850000000
1!
1#
1%
1&
#36900000000
0!
0%
#36950000000
1!
1%
#37000000000
0!
0"
0$
0%
#37050000000
1!
1%
#37100000000
0!
0%
#37150000000
1!
1%
#37200000000
0!
0%
#37250000000
1!
1%
#37300000000
0!
0%
#37350000000
1!
1%
#37400000000
0!
0%
#37450000000
1!
1%
#37500000000
0!
0%
#37550000000
1!
1%
#37600000000
0!
0%
#37650000000
1!
1%
#37700000000
0!
0%
#37750000000
1!
1%
#37800000000
0!
0%
#37850000000
1!
1%
#37900000000
0!
0%
#37950000000
1!
1%
#38000000000
0!
1"
1$
0%
#38050000000
1!
0#
1%
0&
#38100000000
0!
0%
#38150000000
1!
1#
1%
1&
#38200000000
0!
0%
#38250000000
1!
1%
#38300000000
0!
0%
#38350000000
1!
0#
1%
0&
#38400000000
0!
0%
#38450000000
1!
1#
1%
1&
#38500000000
0!
0%
#38550000000
1!
1%
#38600000000
0!
0%
#38650000000
1!
0#
1%
0&
#38700000000
0!
0%
#38750000000
1!
1#
1%
1&
#38800000000
0!
0%
#38850000000
1!
1%
#38900000000
0!
0%
#38950000000
1!
0#
1%
0&
#39000000000
0!
0"
0$
0%
#39050000000
1!
1%
#39100000000
0!
0%
#39150000000
1!
1%
#39200000000
0!
0%
#39250000000
1!
1%
#39300000000
0!
0%
#39350000000
1!
1%
#39400000000
0!
0%
#39450000000
1!
1%
#39500000000
0!
0%
#39550000000
1!
1%
#39600000000
0!
0%
#39650000000
1!
1%
#39700000000
0!
0%
#39750000000
1!
1%
#39800000000
0!
0%
#39850000000
1!
1%
#39900000000
0!
0%
#39950000000
1!
1%
#40000000000
0!
1"
1$
0%
#40050000000
1!
1#
1%
1&
#40100000000
0!
0%
#40150000000
1!
1%
#40200000000
0!
0%
#40250000000
1!
0#
1%
0&
#40300000000
0!
0%
#40350000000
1!
1#
1%
1&
#40400000000
0!
0%
#40450000000
1!
1%
#40500000000
0!
0%
#40550000000
1!
0#
1%
0&
#40600000000
0!
0%
#40650000000
1!
1#
1%
1&
#40700000000
0!
0%
#40750000000
1!
1%
#40800000000
0!
0%
#40850000000
1!
0#
1%
0&
#40900000000
0!
0%
#40950000000
1!
1#
1%
1&
#41000000000
0!
0"
0$
0%
#41050000000
1!
0#
1%
0&
#41100000000
0!
0%
#41150000000
1!
1%
#41200000000
0!
0%
#41250000000
1!
1%
#41300000000
0!
0%
#41350000000
1!
1%
#41400000000
0!
0%
#41450000000
1!
1%
#41500000000
0!
0%
#41550000000
1!
1%
#41600000000
0!
0%
#41650000000
1!
1%
#41700000000
0!
0%
#41750000000
1!
1%
#41800000000
0!
0%
#41850000000
1!
1%
#41900000000
0!
0%
#41950000000
1!
1%
#42000000000
0!
1"
1$
0%
#42050000000
1!
1#
1%
1&
#42100000000
0!
0%
#42150000000
1!
0#
1%
0&
#42200000000
0!
0%
#42250000000
1!
1#
1%
1&
#42300000000
0!
0%
#42350000000
1!
1%
#42400000000
0!
0%
#42450000000
1!
0#
1%
0&
#42500000000
0!
0%
#42550000000
1!
1#
1%
1&
#42600000000
0!
0%
#42650000000
1!
1%
#42700000000
0!
0%
#42750000000
1!
0#
1%
0&
#42800000000
0!
0%
#42850000000
1!
1#
1%
1&
#42900000000
0!
0%
#42950000000
1!
1%
#43000000000
0!
0"
0$
0%
#43050000000
1!
1%
#43100000000
0!
0%
#43150000000
1!
1%
#43200000000
0!
0%
#43250000000
1!
1%
#43300000000
0!
0%
#43350000000
1!
1%
#43400000000
0!
0%
#43450000000
1!
1%
#43500000000
0!
0%
#43550000000
1!
1%
#43600000000
0!
0%
#43650000000
1!
1%
#43700000000
0!
0%
#43750000000
1!
1%
#43800000000
0!
0%
#43850000000
1!
1%
#43900000000
0!
0%
#43950000000
1!
1%
#44000000000
0!
1"
1$
0%
#44050000000
1!
0#
1%
0&
#44100000000
0!
0%
#44150000000
1!
1#
1%
1&
#44200000000
0!
0%
#44250000000
1!
1%
#44300000000
0!
0%
#44350000000
1!
0#
1%
0&
#44400000000
0!
0%
#44450000000
1!
1#
1%
1&
#44500000000
0!
0%
#44550000000
1!
1%
#44600000000
0!
0%
#44650000000
1!
0#
1%
0&
#44700000000
0!
0%
#44750000000
1!
1#
1%
1&
#44800000000
0!
0%
#44850000000
1!
1%
#44900000000
0!
0%
#44950000000
1!
0#
1%
0&
#45000000000
0!
0"
0$
0%
#45050000000
1!
1%
#45100000000
0!
0%
#45150000000
1!
1%
#45200000000
0!
0%
#45250000000
1!
1%
#45300000000
0!
0%
#45350000000
1!
1%
#45400000000
0!
0%
#45450000000
1!
1%
#45500000000
0!
0%
#45550000000
1!
1%
#45600000000
0!
0%
#45650000000
1!
1%
#45700000000
0!
0%
#45750000000
1!
1%
#45800000000
0!
0%
#45850000000
1!
1%
#45900000000
0!
0%
#45950000000
1!
1%
#46000000000
0!
1"
1$
0%
#46050000000
1!
1#
1%
1&
#46100000000
0!
0%
#46150000000
1!
1%
#46200000000
0!
0%
#46250000000
1!
0#
1%
0&
#46300000000
0!
0%
#46350000000
1!
1#
1%
1&
#46400000000
0!
0%
#46450000000
1!
1%
#46500000000
0!
0%
#46550000000
1!
0#
1%
0&
#46600000000
0!
0%
#46650000000
1!
1#
1%
1&
#46700000000
0!
0%
#46750000000
1!
1%
#46800000000
0!
0%
#46850000000
1!
0#
1%
0&
#46900000000
0!
0%
#46950000000
1!
1#
1%
1&
#47000000000
0!
0"
0$
0%
#47050000000
1!
0#
1%
0&
#47100000000
0!
0%
#47150000000
1!
1%
#47200000000
0!
0%
#47250000000
1!
1%
#47300000000
0!
0%
#47350000000
1!
1%
#47400000000
0!
0%
#47450000000
1!
1%
#47500000000
0!
0%
#47550000000
1!
1%
#47600000000
0!
0%
#47650000000
1!
1%
#47700000000
0!
0%
#47750000000
1!
1%
#47800000000
0!
0%
#47850000000
1!
1%
#47900000000
0!
0%
#47950000000
1!
1%
#48000000000
0!
1"
1$
0%
#48050000000
1!
1#
1%
1&
#48100000000
0!
0%
#48150000000
1!
0#
1%
0&
#48200000000
0!
0%
#48250000000
1!
1#
1%
1&
#48300000000
0!
0%
#48350000000
1!
1%
#48400000000
0!
0%
#48450000000
1!
0#
1%
0&
#48500000000
0!
0%
#48550000000
1!
1#
1%
1&
#48600000000
0!
0%
#48650000000
1!
1%
#48700000000
0!
0%
#48750000000
1!
0#
1%
0&
#48800000000
0!
0%
#48850000000
1!
1#
1%
1&
#48900000000
0!
0%
#48950000000
1!
1%
#49000000000
0!
0"
0$
0%
#49050000000
1!
1%
#49100000000
0!
0%
#49150000000
1!
1%
#49200000000
0!
0%
#49250000000
1!
1%
#49300000000
0!
0%
#49350000000
1!
1%
#49400000000
0!
0%
#49450000000
1!
1%
#49500000000
0!
0%
#49550000000
1!
1%
#49600000000
0!
0%
#49650000000
1!
1%
#49700000000
0!
0%
#49750000000
1!
1%
#49800000000
0!
0%
#49850000000
1!
1%
#49900000000
0!
0%
#49950000000
1!
1%
#50000000000
0!
1"
1$
0%
#50050000000
1!
0#
1%
0&
#50100000000
0!
0%
#50150000000
1!
1#
1%
1&
#50200000000
0!
0%
#50250000000
1!
1%
#50300000000
0!
0%
#50350000000
1!
0#
1%
0&
#50400000000
0!
0%
#50450000000
1!
1#
1%
1&
#50500000000
0!
0%
#50550000000
1!
1%
#50600000000
0!
0%
#50650000000
1!
0#
1%
0&
#50700000000
0!
0%
#50750000000
1!
1#
1%
1&
#50800000000
0!
0%
#50850000000
1!
1%
#50900000000
0!
0%
#50950000000
1!
0#
1%
0&
#51000000000
0!
0"
0$
0%
